{
  "items": [
    {
      "fileName": "1.xls",
      "keywordCount": 482,
      "keywords": [],
      "searchCountInPC": 865270,
      "searchCountInMobile": 7591350,
      "productCount": 155162816,
      "clickCount": 9865633.1,
      "totalSearchCount": 8456620,
      "totalCompeteRate": 0.054501588834273286,
      "totalClickRate": 1.1666165796736758
    },
    {
      "fileName": "2.xls",
      "keywordCount": 478,
      "keywords": [],
      "searchCountInPC": 906940,
      "searchCountInMobile": 7707610,
      "productCount": 144278492,
      "clickCount": 9445042.200000001,
      "totalSearchCount": 8614550,
      "totalCompeteRate": 0.059707790680263,
      "totalClickRate": 1.096405755378981
    },
    {
      "fileName": "3.xls",
      "keywordCount": 482,
      "keywords": [],
      "searchCountInPC": 842520,
      "searchCountInMobile": 7399190,
      "productCount": 148649964,
      "clickCount": 10454000.099999994,
      "totalSearchCount": 8241710,
      "totalCompeteRate": 0.055443740302553994,
      "totalClickRate": 1.2684261033207906
    },
    {
      "fileName": "4.xls",
      "keywordCount": 483,
      "keywords": [],
      "searchCountInPC": 771530,
      "searchCountInMobile": 6727460,
      "productCount": 143140393,
      "clickCount": 9131496.799999997,
      "totalSearchCount": 7498990,
      "totalCompeteRate": 0.0523890555477237,
      "totalClickRate": 1.2176968898478324
    },
    {
      "fileName": "5.xls",
      "keywordCount": 481,
      "keywords": [],
      "searchCountInPC": 768720,
      "searchCountInMobile": 6499700,
      "productCount": 146479632,
      "clickCount": 8839258.099999996,
      "totalSearchCount": 7268420,
      "totalCompeteRate": 0.04962068719560956,
      "totalClickRate": 1.2161182347745447
    },
    {
      "fileName": "6.xls",
      "keywordCount": 484,
      "keywords": [],
      "searchCountInPC": 861210,
      "searchCountInMobile": 7139390,
      "productCount": 151635724,
      "clickCount": 9621881.599999994,
      "totalSearchCount": 8000600,
      "totalCompeteRate": 0.052761973161416766,
      "totalClickRate": 1.2026450016248773
    },
    {
      "fileName": "7.xls",
      "keywordCount": 479,
      "keywords": [],
      "searchCountInPC": 833200,
      "searchCountInMobile": 6985000,
      "productCount": 137004056,
      "clickCount": 9306055.999999985,
      "totalSearchCount": 7818200,
      "totalCompeteRate": 0.05706546381371366,
      "totalClickRate": 1.1903067202169277
    },
    {
      "fileName": "8.xls",
      "keywordCount": 477,
      "keywords": [],
      "searchCountInPC": 859100,
      "searchCountInMobile": 7352810,
      "productCount": 155991083,
      "clickCount": 10180292.49999998,
      "totalSearchCount": 8211910,
      "totalCompeteRate": 0.05264345783149669,
      "totalClickRate": 1.2396984988875888
    },
    {
      "fileName": "9.xls",
      "keywordCount": 480,
      "keywords": [],
      "searchCountInPC": 923110,
      "searchCountInMobile": 7814090,
      "productCount": 148255481,
      "clickCount": 10691927.899999985,
      "totalSearchCount": 8737200,
      "totalCompeteRate": 0.05893340294110273,
      "totalClickRate": 1.2237247516366783
    },
    {
      "fileName": "10.xls",
      "keywordCount": 477,
      "keywords": [],
      "searchCountInPC": 756510,
      "searchCountInMobile": 6233410,
      "productCount": 141312963,
      "clickCount": 7686700.8999999985,
      "totalSearchCount": 6989920,
      "totalCompeteRate": 0.04946411038030531,
      "totalClickRate": 1.0996836730606356
    },
    {
      "fileName": "11.xls",
      "keywordCount": 481,
      "keywords": [],
      "searchCountInPC": 832660,
      "searchCountInMobile": 6912620,
      "productCount": 142168455,
      "clickCount": 8669310.999999998,
      "totalSearchCount": 7745280,
      "totalCompeteRate": 0.054479596053850346,
      "totalClickRate": 1.1193024655015698
    },
    {
      "fileName": "12.xls",
      "keywordCount": 479,
      "keywords": [],
      "searchCountInPC": 785520,
      "searchCountInMobile": 6276790,
      "productCount": 135110130,
      "clickCount": 7394742.400000002,
      "totalSearchCount": 7062310,
      "totalCompeteRate": 0.05227076607801354,
      "totalClickRate": 1.047071340680316
    }
  ],
  "category1": "패션잡화",
  "category2": "남성가방",
  "keywordCount": 5763,
  "searchCountInPC": 10006290,
  "searchCountInMobile": 84639420,
  "productCount": 1749189189,
  "clickCount": 111286342.59999993,
  "totalSearchCount": 94645710,
  "totalCompeteRate": 0.054108332360611223,
  "totalClickRate": 1.1758202521804733
}